piccata/__init__.py
piccata/block_transfer.py
piccata/constants.py
piccata/core.py
piccata/message.py
piccata/option.py
piccata/resource.py
piccata/types.py
transport/__init__.py
transport/base.py
transport/tester.py
transport/tsocket.py
piccata-2.0.3.dist-info/LICENSE
piccata-2.0.3.dist-info/METADATA
piccata-2.0.3.dist-info/WHEEL
piccata-2.0.3.dist-info/top_level.txt
piccata-2.0.3.dist-info/RECORD
